cnvpytor/__init__.py
cnvpytor/__main__.py
cnvpytor/bam.py
cnvpytor/export.py
cnvpytor/fasta.py
cnvpytor/genome.py
cnvpytor/io.py
cnvpytor/pool.py
cnvpytor/root.py
cnvpytor/utils.py
cnvpytor/vcf.py
cnvpytor/version.py
cnvpytor/viewer.py
cnvpytor/viewparams.py
cnvpytor/data/readme.txt
cnvpytor/imgs/cnvpytor.png
cnvpytor/imgs/cnvpytor_640.png
cnvpytor/imgs/cnvpytor_w.png
cnvpytor/imgs/cnvpytor_w_640.png
CNVpytor-1.0b3.dist-info/LICENSE
CNVpytor-1.0b3.dist-info/METADATA
CNVpytor-1.0b3.dist-info/WHEEL
CNVpytor-1.0b3.dist-info/entry_points.txt
CNVpytor-1.0b3.dist-info/top_level.txt
CNVpytor-1.0b3.dist-info/RECORD
