Metadata-Version: 2.1
Name: CNVpytor
Version: 1.0b3
Summary: Python extension of CNVnator
Home-page: https://github.com/abyzovlab/CNVpytor
Author: Milovan Suvakov, Abyzov Lab, Mayo Clinic
Author-email: suvakov@gmail.com
License: UNKNOWN
Platform: UNKNOWN
Classifier: Development Status :: 3 - Alpha
Classifier: Programming Language :: Python :: 2
Classifier: Programming Language :: Python :: 2.7
Classifier: Programming Language :: Python :: 3
Classifier: Programming Language :: Python :: 3.5
Classifier: Programming Language :: Python :: 3.6
Classifier: Programming Language :: Python :: 3.7
Classifier: License :: OSI Approved :: MIT License
Classifier: Operating System :: OS Independent
Requires-Dist: gnureadline
Requires-Dist: pathlib (>=1.0)
Requires-Dist: requests (>=2.0)
Requires-Dist: pysam (>=0.15)
Requires-Dist: numpy (>=1.16)
Requires-Dist: scipy (>=1.1)
Requires-Dist: matplotlib (>=2.2)
Requires-Dist: h5py (>=2.9)
